ap_resource_monitor/__init__.py
ap_resource_monitor/monitor.py
ap_resource_monitor-0.1.3.dist-info/LICENSE
ap_resource_monitor-0.1.3.dist-info/METADATA
ap_resource_monitor-0.1.3.dist-info/WHEEL
ap_resource_monitor-0.1.3.dist-info/top_level.txt
ap_resource_monitor-0.1.3.dist-info/RECORD
