Metadata-Version: 2.1
Name: ap_resource_monitor
Version: 0.1.3
Summary: A Python library for monitoring access point resource usage.
Home-page: https://github.com/AirowireAILabs/ap_resource_monitor
Author: AirowireAILabs
Author-email: Airowire AI Labs <ailabs@airowire.com>
License: MIT License
Project-URL: Homepage, https://github.com/AirowireAILabs/ap_resource_monitor
Project-URL: Repository, https://github.com/AirowireAILabs/ap_resource_monitor
Project-URL: Bug Tracker, https://github.com/AirowireAILabs/ap_resource_monitor/issues
Requires-Python: >=3.6
License-File: LICENSE
Requires-Dist: requests >=2.25.0
Requires-Dist: numpy >=1.19.0
